cabinetry/__init__.py
cabinetry/configuration.py
cabinetry/histo.py
cabinetry/model_utils.py
cabinetry/py.typed
cabinetry/route.py
cabinetry/smooth.py
cabinetry/tabulate.py
cabinetry/workspace.py
cabinetry/cli/__init__.py
cabinetry/contrib/__init__.py
cabinetry/contrib/histogram_creator.py
cabinetry/contrib/histogram_reader.py
cabinetry/fit/__init__.py
cabinetry/fit/results_containers.py
cabinetry/schemas/config.json
cabinetry/templates/__init__.py
cabinetry/templates/builder.py
cabinetry/templates/collector.py
cabinetry/templates/postprocessor.py
cabinetry/templates/utils.py
cabinetry/visualize/__init__.py
cabinetry/visualize/plot_model.py
cabinetry/visualize/plot_result.py
cabinetry/visualize/utils.py
cabinetry-0.6.0.dist-info/LICENSE
cabinetry-0.6.0.dist-info/METADATA
cabinetry-0.6.0.dist-info/WHEEL
cabinetry-0.6.0.dist-info/entry_points.txt
cabinetry-0.6.0.dist-info/top_level.txt
cabinetry-0.6.0.dist-info/RECORD
