Metadata-Version: 2.1
Name: cabinetry
Version: 0.6.0
Summary: design and steer profile likelihood fits
Home-page: https://github.com/scikit-hep/cabinetry
Author: Alexander Held
License: BSD 3-Clause
Classifier: Development Status :: 3 - Alpha
Classifier: Programming Language :: Python :: 3.8
Classifier: Programming Language :: Python :: 3.9
Classifier: Programming Language :: Python :: 3.10
Classifier: Programming Language :: Python :: 3.11
Classifier: License :: OSI Approved :: BSD License
Classifier: Topic :: Scientific/Engineering
Classifier: Topic :: Scientific/Engineering :: Physics
Requires-Python: >=3.8
License-File: LICENSE
Requires-Dist: pyhf[minuit]~=0.7.0
Requires-Dist: boost_histogram>=1.0.0
Requires-Dist: tabulate>=0.8.1
Requires-Dist: matplotlib>=3.5.0
Requires-Dist: numpy
Requires-Dist: pyyaml
Requires-Dist: iminuit
Requires-Dist: jsonschema
Requires-Dist: click
Requires-Dist: scipy
Requires-Dist: packaging
Provides-Extra: contrib
Requires-Dist: uproot>=4.1.5; extra == "contrib"
Provides-Extra: test
Requires-Dist: black; extra == "test"
Requires-Dist: check-manifest; extra == "test"
Requires-Dist: flake8; extra == "test"
Requires-Dist: flake8-bugbear; extra == "test"
Requires-Dist: flake8-import-order; extra == "test"
Requires-Dist: flake8-print; extra == "test"
Requires-Dist: mypy; extra == "test"
Requires-Dist: pydocstyle; extra == "test"
Requires-Dist: pytest; extra == "test"
Requires-Dist: pytest-cov>=2.6.1; extra == "test"
Requires-Dist: typeguard!=4.0.1,!=4.1.*,>=4.0.0; extra == "test"
Requires-Dist: types-PyYAML; extra == "test"
Requires-Dist: types-tabulate; extra == "test"
Requires-Dist: uproot>=4.1.5; extra == "test"
Provides-Extra: pyhf-backends
Requires-Dist: pyhf[backends]; extra == "pyhf-backends"
Provides-Extra: docs
Requires-Dist: sphinx!=5.2.0.post0; extra == "docs"
Requires-Dist: sphinx-click; extra == "docs"
Requires-Dist: sphinx-copybutton; extra == "docs"
Requires-Dist: sphinx-jsonschema; extra == "docs"
Requires-Dist: sphinx-rtd-theme; extra == "docs"
Provides-Extra: develop
Requires-Dist: black; extra == "develop"
Requires-Dist: check-manifest; extra == "develop"
Requires-Dist: flake8; extra == "develop"
Requires-Dist: flake8-bugbear; extra == "develop"
Requires-Dist: flake8-import-order; extra == "develop"
Requires-Dist: flake8-print; extra == "develop"
Requires-Dist: mypy; extra == "develop"
Requires-Dist: pre-commit; extra == "develop"
Requires-Dist: pydocstyle; extra == "develop"
Requires-Dist: pytest; extra == "develop"
Requires-Dist: pytest-cov>=2.6.1; extra == "develop"
Requires-Dist: sphinx!=5.2.0.post0; extra == "develop"
Requires-Dist: sphinx-click; extra == "develop"
Requires-Dist: sphinx-copybutton; extra == "develop"
Requires-Dist: sphinx-jsonschema; extra == "develop"
Requires-Dist: sphinx-rtd-theme; extra == "develop"
Requires-Dist: twine; extra == "develop"
Requires-Dist: typeguard!=4.0.1,!=4.1.*,>=4.0.0; extra == "develop"
Requires-Dist: types-PyYAML; extra == "develop"
Requires-Dist: types-tabulate; extra == "develop"
Requires-Dist: uproot>=4.1.5; extra == "develop"
Provides-Extra: complete
Requires-Dist: black; extra == "complete"
Requires-Dist: check-manifest; extra == "complete"
Requires-Dist: flake8; extra == "complete"
Requires-Dist: flake8-bugbear; extra == "complete"
Requires-Dist: flake8-import-order; extra == "complete"
Requires-Dist: flake8-print; extra == "complete"
Requires-Dist: mypy; extra == "complete"
Requires-Dist: pre-commit; extra == "complete"
Requires-Dist: pydocstyle; extra == "complete"
Requires-Dist: pyhf[backends]; extra == "complete"
Requires-Dist: pytest; extra == "complete"
Requires-Dist: pytest-cov>=2.6.1; extra == "complete"
Requires-Dist: sphinx!=5.2.0.post0; extra == "complete"
Requires-Dist: sphinx-click; extra == "complete"
Requires-Dist: sphinx-copybutton; extra == "complete"
Requires-Dist: sphinx-jsonschema; extra == "complete"
Requires-Dist: sphinx-rtd-theme; extra == "complete"
Requires-Dist: twine; extra == "complete"
Requires-Dist: typeguard!=4.0.1,!=4.1.*,>=4.0.0; extra == "complete"
Requires-Dist: types-PyYAML; extra == "complete"
Requires-Dist: types-tabulate; extra == "complete"
Requires-Dist: uproot>=4.1.5; extra == "complete"
